{
  "name": "avatar/UUVavN9OYF9g8cMY9BV5jRWB4v1o/UUVavN9OYF9g8cMY9BV5jRWB4v1o1699661705395",
  "bucket": "connect-411.appspot.com",
  "metageneration": 1,
  "generation": 1699661705500,
  "contentType": "image/jpeg",
  "storageClass": "STANDARD",
  "contentDisposition": "inline",
  "downloadTokens": [
    "34845778-7e69-4e8f-ba8a-fb65ef8519fd"
  ],
  "etag": "ESLPhuD5EBRplfdjN54dwW3YKbo",
  "customMetadata": {},
  "timeCreated": "2023-11-11T00:15:05.500Z",
  "updated": "2023-11-11T00:15:05.500Z",
  "size": 1610,
  "md5Hash": "sTWYC0WVm7AzbfAacQ0mkw==",
  "crc32c": "2600431012"
}