{
  "name": "avatar/UUVavN9OYF9g8cMY9BV5jRWB4v1o/UUVavN9OYF9g8cMY9BV5jRWB4v1o1699137089142",
  "bucket": "connect-411.appspot.com",
  "metageneration": 1,
  "generation": 1699137089120,
  "contentType": "image/jpeg",
  "storageClass": "STANDARD",
  "contentDisposition": "inline",
  "downloadTokens": [
    "9090a55c-e712-4050-8b3f-1cf628fb1c0a"
  ],
  "etag": "HupSNWto5mHs9n3FYNCe5tCieaM",
  "customMetadata": {},
  "timeCreated": "2023-11-04T22:31:29.120Z",
  "updated": "2023-11-04T22:31:29.120Z",
  "size": 435444,
  "md5Hash": "o0NRqVabhyxhPNtRx8Q88g==",
  "crc32c": "2274417071"
}