{
  "name": "avatar/UUVavN9OYF9g8cMY9BV5jRWB4v1o/UUVavN9OYF9g8cMY9BV5jRWB4v1o1698941436875",
  "bucket": "connect-411.appspot.com",
  "metageneration": 1,
  "generation": 1698941437029,
  "contentType": "image/jpeg",
  "storageClass": "STANDARD",
  "contentDisposition": "inline",
  "downloadTokens": [
    "c0f33fc0-b05f-4aca-879c-1ecc0896f5a0"
  ],
  "etag": "QlLZk8x52I13g8fQjG5cykgVIN8",
  "customMetadata": {},
  "timeCreated": "2023-11-02T16:10:37.029Z",
  "updated": "2023-11-02T16:10:37.029Z",
  "size": 10871,
  "md5Hash": "mSxz9UIguhehoU3Bwd/CKA==",
  "crc32c": "4281722024"
}